open_stocks_mcp/__init__.py
open_stocks_mcp/config.py
open_stocks_mcp/logging_config.py
open_stocks_mcp/monitoring.py
open_stocks_mcp/py.typed
open_stocks_mcp/client/__init__.py
open_stocks_mcp/client/app.py
open_stocks_mcp/server/__init__.py
open_stocks_mcp/server/app.py
open_stocks_mcp/server/http_transport.py
open_stocks_mcp/tools/__init__.py
open_stocks_mcp/tools/error_handling.py
open_stocks_mcp/tools/rate_limiter.py
open_stocks_mcp/tools/robinhood_account_features_tools.py
open_stocks_mcp/tools/robinhood_account_tools.py
open_stocks_mcp/tools/robinhood_advanced_portfolio_tools.py
open_stocks_mcp/tools/robinhood_crypto_tools.py
open_stocks_mcp/tools/robinhood_dividend_tools.py
open_stocks_mcp/tools/robinhood_market_data_tools.py
open_stocks_mcp/tools/robinhood_options_tools.py
open_stocks_mcp/tools/robinhood_order_tools.py
open_stocks_mcp/tools/robinhood_stock_tools.py
open_stocks_mcp/tools/robinhood_tools.py
open_stocks_mcp/tools/robinhood_trading_tools.py
open_stocks_mcp/tools/robinhood_user_profile_tools.py
open_stocks_mcp/tools/robinhood_watchlist_tools.py
open_stocks_mcp/tools/session_manager.py
open_stocks_mcp-0.6.4.dist-info/METADATA
open_stocks_mcp-0.6.4.dist-info/WHEEL
open_stocks_mcp-0.6.4.dist-info/entry_points.txt
open_stocks_mcp-0.6.4.dist-info/licenses/LICENSE
open_stocks_mcp-0.6.4.dist-info/RECORD
