Metadata-Version: 2.4
Name: open-stocks-mcp
Version: 0.6.4
Summary: MCP Server based on open stock API packages like Robin Stocks
Project-URL: Homepage, https://github.com/Open-Agent-Tools/open-stocks-mcp
Project-URL: Bug Tracker, https://github.com/Open-Agent-Tools/open-stocks-mcp/issues
Project-URL: Documentation, https://github.com/Open-Agent-Tools/open-stocks-mcp#readme
Project-URL: Source Code, https://github.com/Open-Agent-Tools/open-stocks-mcp
Author-email: Wes Etheredge <jwesleye@gmail.com>
Maintainer-email: Wes Etheredge <jwesleye@gmail.com>
License:                                  Apache License
License-File: LICENSE
Keywords: api,finance,mcp,robin-stocks,stocks,trading
Classifier: Development Status :: 3 - Alpha
Classifier: Intended Audience :: Developers
Classifier: Intended Audience :: Financial and Insurance Industry
Classifier: License :: OSI Approved :: Apache Software License
Classifier: Operating System :: OS Independent
Classifier: Programming Language :: Python :: 3
Classifier: Programming Language :: Python :: 3.11
Classifier: Programming Language :: Python :: 3.12
Classifier: Programming Language :: Python :: 3.13
Classifier: Topic :: Office/Business :: Financial :: Investment
Classifier: Topic :: Software Development :: Libraries :: Python Modules
Classifier: Typing :: Typed
Requires-Python: >=3.11
Requires-Dist: aiofiles>=23.2.0
Requires-Dist: anyio>=4.5
Requires-Dist: cachetools>=5.3.0
Requires-Dist: click>=8.0.0
Requires-Dist: cryptography>=41.0.0
Requires-Dist: fastapi>=0.104.0
Requires-Dist: jsonrpclib-pelix>=0.4.3
Requires-Dist: mcp>=1.0.0
Requires-Dist: pydantic>=2.0.0
Requires-Dist: python-dotenv>=1.0.0
Requires-Dist: requests>=2.31.0
Requires-Dist: robin-stocks>=3.0.0
Requires-Dist: sse-starlette>=1.8.0
Requires-Dist: uvicorn>=0.24.0
Provides-Extra: dev
Requires-Dist: black>=24.0.0; extra == 'dev'
Requires-Dist: httpx>=0.26.0; extra == 'dev'
Requires-Dist: mypy>=1.13.0; extra == 'dev'
Requires-Dist: pre-commit>=4.0.0; extra == 'dev'
Requires-Dist: pytest-asyncio>=0.23.0; extra == 'dev'
Requires-Dist: pytest-mock>=3.14.0; extra == 'dev'
Requires-Dist: pytest>=8.0.0; extra == 'dev'
Requires-Dist: ruff>=0.7.0; extra == 'dev'
